miniconfig/__init__.py
miniconfig/exceptions.py
miniconfig/langhelpers.py
miniconfig/modulelib.py
miniconfig/py.typed
miniconfig/types.py
miniconfig-0.6.0.dist-info/METADATA
miniconfig-0.6.0.dist-info/WHEEL
miniconfig-0.6.0.dist-info/top_level.txt
miniconfig-0.6.0.dist-info/RECORD
